autoagentsai/__init__.py
autoagentsai/api/ChatAPI.py
autoagentsai/api/GraphAPI.py
autoagentsai/api/KbAPI.py
autoagentsai/client/ChatClient.py
autoagentsai/client/CrawlClient.py
autoagentsai/client/KbClient.py
autoagentsai/client/MCPClient.py
autoagentsai/client/SupabaseClient.py
autoagentsai/client/__init__.py
autoagentsai/datascience/DSAgent.py
autoagentsai/datascience/__init__.py
autoagentsai/dify/DifyGraph.py
autoagentsai/dify/DifyTypes.py
autoagentsai/dify/__init__.py
autoagentsai/fonts/SourceHanSansSC-Regular.otf
autoagentsai/fonts/__init__.py
autoagentsai/graph/AutoWorkFlow.py
autoagentsai/graph/FlowGraph.py
autoagentsai/graph/FlowInterpreter.py
autoagentsai/graph/NodeRegistry.py
autoagentsai/graph/Text2Workflow.py
autoagentsai/graph/Utils.py
autoagentsai/graph/__init__.py
autoagentsai/graph/prompt.md
autoagentsai/publish/Publisher.py
autoagentsai/publish/__init__.py
autoagentsai/react/ReActAgent.py
autoagentsai/react/__init__.py
autoagentsai/sandbox/E2BSandbox.py
autoagentsai/sandbox/LocalSandbox.py
autoagentsai/sandbox/__init__.py
autoagentsai/slide/README.md
autoagentsai/slide/SlideAgent.py
autoagentsai/slide/__init__.py
autoagentsai/slide/html2pptx_agent.py
autoagentsai/slide/pptx2pptx_agent.py
autoagentsai/tools/ToolManager.py
autoagentsai/tools/__init__.py
autoagentsai/types/ChatTypes.py
autoagentsai/types/GraphTypes.py
autoagentsai/types/KbTypes.py
autoagentsai/types/__init__.py
autoagentsai/utils/__init__.py
autoagentsai/utils/convertor.py
autoagentsai/utils/downloader.py
autoagentsai/utils/extractor.py
autoagentsai/utils/uploader.py
autoagentsai-0.1.36.dist-info/METADATA
autoagentsai-0.1.36.dist-info/WHEEL
autoagentsai-0.1.36.dist-info/entry_points.txt
autoagentsai-0.1.36.dist-info/RECORD
