Metadata-Version: 2.4
Name: autoagentsai
Version: 0.1.36
Summary: SDK for interacting with Autoagents.ai API
Author-email: Hehua Fan <forhheart5532@gmail.com>
Requires-Python: >=3.11
Requires-Dist: bs4
Requires-Dist: e2b-code-interpreter
Requires-Dist: matplotlib
Requires-Dist: mcp[cli]
Requires-Dist: openpyxl
Requires-Dist: pandas
Requires-Dist: playwright
Requires-Dist: psycopg2-binary
Requires-Dist: pydantic>=2.11.7
Requires-Dist: python-pptx>=0.6.21
Requires-Dist: requests>=2.32.4
Requires-Dist: seaborn
Requires-Dist: sqlalchemy
Requires-Dist: supabase
